{
  "chapters": {
    "1": {
      "pendingViews": 8,
      "lastIncrement": "2025-12-24T15:49:01.104Z",
      "lastUpdate": "2025-12-24T00:25:47+07:00"
    },
    "2": {
      "pendingViews": 2,
      "lastIncrement": "2025-12-24T15:58:03.660Z",
      "lastUpdate": "2025-12-24T00:25:47+07:00"
    },
    "3": {
      "pendingViews": 3,
      "lastIncrement": "2025-12-24T16:05:45.155Z",
      "lastUpdate": "2025-12-24T00:25:47+07:00"
    },
    "4.1": {
      "pendingViews": 2,
      "lastIncrement": "2025-12-24T16:13:44.483Z",
      "lastUpdate": "2025-12-24T00:25:47+07:00"
    },
    "4.2": {
      "pendingViews": 2,
      "lastIncrement": "2025-12-24T16:16:25.776Z",
      "lastUpdate": "2025-12-24T00:25:47+07:00"
    },
    "5.1": {
      "pendingViews": 2,
      "lastIncrement": "2025-12-24T16:19:46.163Z",
      "lastUpdate": "2025-12-24T00:25:47+07:00"
    },
    "5.2": {
      "pendingViews": 2,
      "lastIncrement": "2025-12-24T16:24:10.814Z",
      "lastUpdate": "2025-12-24T00:25:47+07:00"
    },
    "6.1": {
      "pendingViews": 2,
      "lastIncrement": "2025-12-24T16:27:33.699Z",
      "lastUpdate": "2025-12-24T00:25:47+07:00"
    },
    "6.2": {
      "pendingViews": 2,
      "lastIncrement": "2025-12-24T16:31:26.324Z",
      "lastUpdate": "2025-12-24T00:25:47+07:00"
    },
    "7.1": {
      "pendingViews": 2,
      "lastIncrement": "2025-12-24T16:34:36.600Z",
      "lastUpdate": "2025-12-24T00:25:47+07:00"
    },
    "7.2": {
      "pendingViews": 2,
      "lastIncrement": "2025-12-24T16:39:38.899Z",
      "lastUpdate": "2025-12-24T00:25:47+07:00"
    },
    "8.1": {
      "pendingViews": 2,
      "lastIncrement": "2025-12-24T16:43:43.068Z",
      "lastUpdate": "2025-12-24T00:25:47+07:00"
    },
    "8.2": {
      "pendingViews": 2,
      "lastIncrement": "2025-12-24T16:46:13.269Z",
      "lastUpdate": "2025-12-24T00:25:47+07:00"
    },
    "9.1": {
      "pendingViews": 2,
      "lastIncrement": "2025-12-24T16:49:30.224Z",
      "lastUpdate": "2025-12-24T00:25:47+07:00"
    },
    "9.2": {
      "pendingViews": 2,
      "lastIncrement": "2025-12-24T16:53:56.484Z",
      "lastUpdate": "2025-12-24T00:25:47+07:00"
    },
    "10.1": {
      "pendingViews": 2,
      "lastIncrement": "2025-12-24T16:58:29.140Z",
      "lastUpdate": "2025-12-24T00:25:47+07:00"
    },
    "10.2": {
      "pendingViews": 4,
      "lastIncrement": "2025-12-24T17:05:31.355Z",
      "lastUpdate": "2025-12-24T00:25:47+07:00"
    },
    "11.1": {
      "pendingViews": 2,
      "lastIncrement": "2025-12-24T17:07:16.557Z",
      "lastUpdate": "2025-12-24T00:25:47+07:00"
    },
    "11.2": {
      "pendingViews": 2,
      "lastIncrement": "2025-12-24T17:11:46.810Z",
      "lastUpdate": "2025-12-24T00:25:47+07:00"
    },
    "12.1": {
      "pendingViews": 2,
      "lastIncrement": "2025-12-24T17:14:42.527Z",
      "lastUpdate": "2025-12-24T00:25:47+07:00"
    },
    "12.2": {
      "pendingViews": 4,
      "lastIncrement": "2025-12-24T17:19:59.770Z",
      "lastUpdate": "2025-12-24T00:25:47+07:00"
    },
    "13.1": {
      "pendingViews": 1,
      "lastIncrement": "2025-12-24T10:25:00.964Z",
      "lastUpdate": "2025-12-24T00:25:47+07:00"
    },
    "13.2": {
      "pendingViews": 1,
      "lastIncrement": "2025-12-24T10:25:57.048Z",
      "lastUpdate": "2025-12-24T00:25:47+07:00"
    },
    "14.1": {
      "pendingViews": 5,
      "lastIncrement": "2025-12-24T14:44:47.592Z",
      "lastUpdate": "2025-12-24T00:25:47+07:00"
    }
  },
  "lastUpdated": "2025-12-24T00:25:47+07:00"
}